LICENSE
MANIFEST.in
README.rst
helga_no_more_olga.py
setup.py
helga_no_more_olga.egg-info/PKG-INFO
helga_no_more_olga.egg-info/SOURCES.txt
helga_no_more_olga.egg-info/dependency_links.txt
helga_no_more_olga.egg-info/entry_points.txt
helga_no_more_olga.egg-info/top_level.txt
helga_no_more_olga.egg-info/zip-safe